wtvmeans/__init__.py
wtvmeans/dipmeans.py
wtvmeans/elbow.py
wtvmeans/extra.py
wtvmeans/gmeans.py
wtvmeans/phimeans.py
wtvmeans/wtvmeans.py
wtvmeans/xmeans.py
wtvmeans-1.2.1.dist-info/LICENSE
wtvmeans-1.2.1.dist-info/METADATA
wtvmeans-1.2.1.dist-info/WHEEL
wtvmeans-1.2.1.dist-info/top_level.txt
wtvmeans-1.2.1.dist-info/RECORD
